cryppy_coins/__init__.py
crypto_coins/__init__.py
crypto_coins/crypto_coins.py
crypy_coins-1.0.1.dist-info/METADATA
crypy_coins-1.0.1.dist-info/WHEEL
crypy_coins-1.0.1.dist-info/top_level.txt
crypy_coins-1.0.1.dist-info/RECORD
