Metadata-Version: 2.1
Name: crypy-coins
Version: 1.0.1
Summary: read README.md from github
Home-page: https://github.com/gravitywolfLaCanneAPeche/crypto-coins
Author: Canne à pêche
Author-email: gravitywolf.loup@gmail.com
License: UNKNOWN
Platform: UNKNOWN
Classifier: Programming Language :: Python :: 3
Classifier: Programming Language :: Python :: 3.9
